{
  "themeName": "我要开信息咨询服务公司",
  "category": "生活服务",
  "items": [
    {
      "scopeId": "c9bacebb337baa01c7c3cf6f3d4e9556",
      "standardItem": "票据信息咨询服务",
      "scopeCode": "L2104",
      "description": "开展票据交易咨询、鉴证、登记、经纪、信息等服务（不含票据融资业务）；为金融机构提供票据信息技术服务。",
      "permitType": 0,
      "detail": {
        "isPermission": "",
        "permitExplain": "",
        "includedItems": "开展票据交易咨询、鉴证、登记、经纪、信息等服务（不含票据融资业务）；为金融机构提供票据信息技术服务。",
        "notIncluded": "",
        "remarks": "",
        "specialTips": ""
      }
    },
    {
      "scopeId": "28e85b3d76f06883290efebeca0fdc3d",
      "standardItem": "企业管理咨询",
      "scopeCode": "L2095",
      "description": "指从事企业管理咨询的活动。\n",
      "permitType": 0,
      "detail": {
        "isPermission": "否",
        "permitExplain": "",
        "includedItems": "企业管理咨询\n",
        "notIncluded": "J2009  证券投资咨询；M2040 工程造价咨询业务；K1009\t房地产咨询；L2056\t旅行社服务网点旅游招徕、咨询服务；L2024\t法律咨询（不包括律师事务所业务）；教育培训；投资咨询；商务信息咨询；心理咨询服务，列入7244（健康咨询）；营养健康咨询服务，列入7244（健康咨询)；体育运动咨询服务，列入7246（体育咨询）；人力资源咨询服务，列入726（人力资源服务）相关行业类别中；创业咨询服务，列入7264（创业指导服务）；信用管理咨询服务、信用评估服务，列入7295（信用服务）；工程咨询，列入7481（工程管理服务）；计算机咨询，列入6560（信息技术咨询服务）；房地产咨询，列入7030（房地产中介服务）；法律咨询，列入7231（律师及相关法律服务）；劳务、就业及职业咨询，列入7269（其他人力资源服务）；广告咨询，列入725（广告业）相关行业类别中；旅游咨询，列入7291（旅行社及相关服务）；科学技术咨询，列入7530（科技中介服务）；吸收存款、融资担保、代客理财等金融相关业务；",
        "remarks": "《工商总局关于扩大开放港澳居民在内地申办个体工商户登记管理工作的意见》（工商个字〔2016〕99号）",
        "specialTips": ""
      }
    },
    {
      "scopeId": "5543ab2329064ab78fc9b8669aa60462",
      "standardItem": "信息咨询服务（不含许可类信息咨询服务）",
      "scopeCode": "L2032",
      "description": "指以专门的知识、技能和经验，进行必要的调查、研究和谋划，向用户提供其所需的信息、意见和方案等服务的经营活动",
      "permitType": 0,
      "detail": {
        "isPermission": "否",
        "permitExplain": "",
        "includedItems": "体育赛事咨询服务；运动员咨询服务；俱乐部咨询服务；全民健身咨询服务；体育管理咨询服务；生产制造咨询；技术转移咨询服务；物流信息咨询；市场信息咨询；科技信息咨询；企业管理信息咨询；互联网信息咨询；创业咨询服务；创业技术转移咨询与策划服务；创业市场开拓咨询与策划服务；商务信息咨询（不含投资类咨询）；汽车信息咨询；日用品信息咨询；安全生产标准化咨询；高考志愿填报咨询；招生信息咨询；建筑材料信息咨询；旅游信息咨询；仓单运营标准化信息咨询；出国签证咨询；",
        "notIncluded": "教育咨询服务；房地产咨询；各类技术咨询；安全咨询服务；企业管理咨询；法律咨询（不包括律师事务所业务）；认证咨询；旅行社服务网点旅游招徕、咨询服务；财务咨询；证券投资咨询；工程造价咨询业务；健康咨询服务（不含诊疗服务）；票据信息咨询服务；企业信用管理咨询服务；涉外调查；职业中介活动；认证服务；呼叫中心；房地产评估；科技中介服务；环境保护与治理咨询，列入7245（环保咨询）；医疗、医药咨询，列入7244（健康咨询）；工程技术咨询，列入7481（工程管理服务）；计算机咨询，列入6560（信息技术咨询服务）；软件咨询，列入651（软件开发）相关行业类别中；科技咨询，列入7530（科技中介服务）；工程勘察咨询,列入7483(工程勘察活动)。\n",
        "remarks": "",
        "specialTips": ""
      }
    }
  ]
}